kalkulacka
