Metadata-Version: 1.1
Name: kalkulacka
Version: 0.2
Summary: A demo calculator
Home-page: https://github.com/encukou/kalkulacka
Author: Petr Viktorin
Author-email: encukou@gmail.com
License: MIT
Platform: UNKNOWN
Classifier: License :: OSI Approved :: MIT License
Classifier: Programming Language :: Python
Classifier: Programming Language :: Python :: 3
Classifier: Programming Language :: Python :: 3.6
